pytoniq_core/__init__.py
pytoniq_core/boc/__init__.py
pytoniq_core/boc/address.py
pytoniq_core/boc/builder.py
pytoniq_core/boc/cell.py
pytoniq_core/boc/deserialize.py
pytoniq_core/boc/exotic.py
pytoniq_core/boc/slice.py
pytoniq_core/boc/tvm_bitarray.py
pytoniq_core/boc/utils.py
pytoniq_core/boc/hashmap/__init__.py
pytoniq_core/boc/hashmap/hashmap.py
pytoniq_core/boc/hashmap/parse.py
pytoniq_core/boc/hashmap/utils.py
pytoniq_core/crypto/__init__.py
pytoniq_core/crypto/ciphers.py
pytoniq_core/crypto/crc.py
pytoniq_core/crypto/keys.py
pytoniq_core/crypto/signature.py
pytoniq_core/proof/__init__.py
pytoniq_core/proof/check_proof.py
pytoniq_core/tl/__init__.py
pytoniq_core/tl/block.py
pytoniq_core/tl/generator.py
pytoniq_core/tl/schemas/lite_api.tl
pytoniq_core/tl/schemas/ton_api.tl
pytoniq_core/tl/schemas/tonlib_api.tl
pytoniq_core/tlb/__init__.py
pytoniq_core/tlb/account.py
pytoniq_core/tlb/block.py
pytoniq_core/tlb/config.py
pytoniq_core/tlb/tlb.py
pytoniq_core/tlb/transaction.py
pytoniq_core/tlb/utils.py
pytoniq_core/tlb/vm_stack.py
pytoniq_core/tlb/custom/__init__.py
pytoniq_core/tlb/custom/nft.py
pytoniq_core/tlb/custom/wallet.py
pytoniq_core-0.1.43.dist-info/METADATA
pytoniq_core-0.1.43.dist-info/WHEEL
pytoniq_core-0.1.43.dist-info/top_level.txt
pytoniq_core-0.1.43.dist-info/RECORD
