Metadata-Version: 2.4
Name: pytoniq-core
Version: 0.1.43
Summary: TON Blockchain SDK
Home-page: https://github.com/yungwine/pytoniq
Author: Maksim Kurbatov
Author-email: cyrbatoff@gmail.com
Classifier: Programming Language :: Python :: 3.9
Classifier: Programming Language :: Python :: 3.10
Classifier: Programming Language :: Python :: 3.11
Classifier: Topic :: Software Development :: Libraries
Requires-Python: >=3.9
Requires-Dist: pycryptodomex>=3.18.0
Requires-Dist: bitarray>=2.6.0
Requires-Dist: requests>=2.31.0
Requires-Dist: x25519>=0.0.2
Requires-Dist: setuptools>=65.5.1
Requires-Dist: PyNaCl>=1.5.0
Dynamic: author
Dynamic: author-email
Dynamic: classifier
Dynamic: description
Dynamic: description-content-type
Dynamic: home-page
Dynamic: requires-dist
Dynamic: requires-python
Dynamic: summary
